fakepdftk/WatermarkUtils.py
fakepdftk/__init__.py
fakepdftk/command_line.py
fakepdftk-0.2.dist-info/LICENSE
fakepdftk-0.2.dist-info/METADATA
fakepdftk-0.2.dist-info/WHEEL
fakepdftk-0.2.dist-info/entry_points.txt
fakepdftk-0.2.dist-info/top_level.txt
fakepdftk-0.2.dist-info/zip-safe
fakepdftk-0.2.dist-info/RECORD
